Workbook

Sheet 說明
A1: 評估二:商業分析模擬 — 計算工作檔
A3: 課程 | B3: 231708 Foundation Studio — 評估任務二
A4: 資料 | B4: Udemy Courses Dataset(Kaggle,n=1203,已剔除缺失值)
A5: 用途 | B5: 本檔以 Excel 公式即時重現報告中 Q1–Q11 的所有統計計算,供核對。
A6: 說明 | B6: 迴歸以 LINEST 估計;虛擬變數基準組為 2011 年與 All Levels。
A8: 工作表導覽
A9: 資料 | B9: 原始 1203 筆資料 + 迴歸用虛擬變數欄
A10: Q1_描述統計 | B10: 六變數平均/中位/眾數/標準差
A11: Q2_頻數 | B11: level 與 year 的次數分布
A12: Q3_t檢定 | B12: 單樣本 t 檢定(評分=65%)
A13: Q4_相關 | B13: price 與 num_subscribers 相關係數
A14: Q5_Q10_迴歸 | B14: 簡單、多元、對數迴歸
A15: Q11_需求曲線 | B15: 指定課程的訂閱人數預測

Sheet 資料
A1: course_id | B1: course_title | C1: url | D1: price | E1: num_subscribers | F1: num_reviews | G1: num_lectures | H1: level | I1: rating | J1: content_duration | K1: freepaid | L1: year | M1: log_num_subscriber | N1: log_price | P1: price_x | Q1: lectures_x | R1: duration_x | S1: y2012 | T1: y2013 | U1: y2014 | V1: y2015 | W1: y2016 | X1: y2017 | Y1: lvBeg | Z1: lvExp | AA1: lvInt | AC1: logprice_x | AD1: lectures_x | AE1: duration_x | AF1: y2012 | AG1: y2013 | AH1: y2014 | AI1: y2015 | AJ1: y2016 | AK1: y2017 | AL1: lvBeg | AM1: lvExp | AN1: lvInt
A2: 41295 | B2: Learn HTML5 Programming From Scratch | C2: https://www.udemy.com/learn-html5-programming-from-scratch/ | D2: 0 | E2: 268923 | F2: 8629 | G2: 45 | H2: Beginner Level | I2: 0.82 | J2: 10.5 | K2: Free | L2: 2013 | M2: 12.50218 | N2: -4.6051702 | P2: =D2 -> 0 | Q2: =G2 -> 45 | R2: =J2 -> 10.5 | S2: =IF($L2=2012,1,0) -> 0 | T2: =IF($L2=2013,1,0) -> 1 | U2: =IF($L2=2014,1,0) -> 0 | V2: =IF($L2=2015,1,0) -> 0 | W2: =IF($L2=2016,1,0) -> 0 | X2: =IF($L2=2017,1,0) -> 0 | Y2: =IF($H2="Beginner Level",1,0) -> 1 | Z2: =IF($H2="Expert Level",1,0) -> 0 | AA2: =IF($H2="Intermediate Level",1,0) -> 0 | AC2: =N2 -> -4.6051702 | AD2: =G2 -> 45 | AE2: =J2 -> 10.5 | AF2: =IF($L2=2012,1,0) -> 0 | AG2: =IF($L2=2013,1,0) -> 1 | AH2: =IF($L2=2014,1,0) -> 0 | AI2: =IF($L2=2015,1,0) -> 0 | AJ2: =IF($L2=2016,1,0) -> 0 | AK2: =IF($L2=2017,1,0) -> 0 | AL2: =IF($H2="Beginner Level",1,0) -> 1 | AM2: =IF($H2="Expert Level",1,0) -> 0 | AN2: =IF($H2="Intermediate Level",1,0) -> 0
A3: 59014 | B3: Coding for Entrepreneurs Basic | C3: https://www.udemy.com/coding-for-entrepreneurs-basic/ | D3: 0 | E3: 161029 | F3: 279 | G3: 27 | H3: Expert Level | I3: 0.69 | J3: 3.5 | K3: Free | L3: 2013 | M3: 11.98934 | N3: -4.6051702 | P3: =D3 -> 0 | Q3: =G3 -> 27 | R3: =J3 -> 3.5 | S3: =IF($L3=2012,1,0) -> 0 | T3: =IF($L3=2013,1,0) -> 1 | U3: =IF($L3=2014,1,0) -> 0 | V3: =IF($L3=2015,1,0) -> 0 | W3: =IF($L3=2016,1,0) -> 0 | X3: =IF($L3=2017,1,0) -> 0 | Y3: =IF($H3="Beginner Level",1,0) -> 0 | Z3: =IF($H3="Expert Level",1,0) -> 1 | AA3: =IF($H3="Intermediate Level",1,0) -> 0 | AC3: =N3 -> -4.6051702 | AD3: =G3 -> 27 | AE3: =J3 -> 3.5 | AF3: =IF($L3=2012,1,0) -> 0 | AG3: =IF($L3=2013,1,0) -> 1 | AH3: =IF($L3=2014,1,0) -> 0 | AI3: =IF($L3=2015,1,0) -> 0 | AJ3: =IF($L3=2016,1,0) -> 0 | AK3: =IF($L3=2017,1,0) -> 0 | AL3: =IF($H3="Beginner Level",1,0) -> 0 | AM3: =IF($H3="Expert Level",1,0) -> 1 | AN3: =IF($H3="Intermediate Level",1,0) -> 0
A4: 625204 | B4: The Web Developer Bootcamp | C4: https://www.udemy.com/the-web-developer-bootcamp/ | D4: 200 | E4: 121584 | F4: 27445 | G4: 342 | H4: Beginner Level | I4: 0.89 | J4: 43 | K4: Paid | L4: 2015 | M4: 11.708361 | N4: 5.2983674 | P4: =D4 -> 200 | Q4: =G4 -> 342 | R4: =J4 -> 43 | S4: =IF($L4=2012,1,0) -> 0 | T4: =IF($L4=2013,1,0) -> 0 | U4: =IF($L4=2014,1,0) -> 0 | V4: =IF($L4=2015,1,0) -> 1 | W4: =IF($L4=2016,1,0) -> 0 | X4: =IF($L4=2017,1,0) -> 0 | Y4: =IF($H4="Beginner Level",1,0) -> 1 | Z4: =IF($H4="Expert Level",1,0) -> 0 | AA4: =IF($H4="Intermediate Level",1,0) -> 0 | AC4: =N4 -> 5.2983674 | AD4: =G4 -> 342 | AE4: =J4 -> 43 | AF4: =IF($L4=2012,1,0) -> 0 | AG4: =IF($L4=2013,1,0) -> 0 | AH4: =IF($L4=2014,1,0) -> 0 | AI4: =IF($L4=2015,1,0) -> 1 | AJ4: =IF($L4=2016,1,0) -> 0 | AK4: =IF($L4=2017,1,0) -> 0 | AL4: =IF($H4="Beginner Level",1,0) -> 1 | AM4: =IF($H4="Expert Level",1,0) -> 0 | AN4: =IF($H4="Intermediate Level",1,0) -> 0
A5: 173548 | B5: Build Your First Website in 1 Week with HTML5 and CSS3 | C5: https://www.udemy.com/build-your-first-website-in-1-week/ | D5: 0 | E5: 120291 | F5: 5924 | G5: 30 | H5: All Levels | I5: 0.78 | J5: 3 | K5: Free | L5: 2014 | M5: 11.697669 | N5: -4.6051702 | P5: =D5 -> 0 | Q5: =G5 -> 30 | R5: =J5 -> 3 | S5: =IF($L5=2012,1,0) -> 0 | T5: =IF($L5=2013,1,0) -> 0 | U5: =IF($L5=2014,1,0) -> 1 | V5: =IF($L5=2015,1,0) -> 0 | W5: =IF($L5=2016,1,0) -> 0 | X5: =IF($L5=2017,1,0) -> 0 | Y5: =IF($H5="Beginner Level",1,0) -> 0 | Z5: =IF($H5="Expert Level",1,0) -> 0 | AA5: =IF($H5="Intermediate Level",1,0) -> 0 | AC5: =N5 -> -4.6051702 | AD5: =G5 -> 30 | AE5: =J5 -> 3 | AF5: =IF($L5=2012,1,0) -> 0 | AG5: =IF($L5=2013,1,0) -> 0 | AH5: =IF($L5=2014,1,0) -> 1 | AI5: =IF($L5=2015,1,0) -> 0 | AJ5: =IF($L5=2016,1,0) -> 0 | AK5: =IF($L5=2017,1,0) -> 0 | AL5: =IF($H5="Beginner Level",1,0) -> 0 | AM5: =IF($H5="Expert Level",1,0) -> 0 | AN5: =IF($H5="Intermediate Level",1,0) -> 0
A6: 764164 | B6: The Complete Web Developer Course 2.0 | C6: https://www.udemy.com/the-complete-web-developer-course-2/ | D6: 200 | E6: 114512 | F6: 22412 | G6: 304 | H6: Beginner Level | I6: 0.55 | J6: 30.5 | K6: Paid | L6: 2016 | M6: 11.648435 | N6: 5.2983674 | P6: =D6 -> 200 | Q6: =G6 -> 304 | R6: =J6 -> 30.5 | S6: =IF($L6=2012,1,0) -> 0 | T6: =IF($L6=2013,1,0) -> 0 | U6: =IF($L6=2014,1,0) -> 0 | V6: =IF($L6=2015,1,0) -> 0 | W6: =IF($L6=2016,1,0) -> 1 | X6: =IF($L6=2017,1,0) -> 0 | Y6: =IF($H6="Beginner Level",1,0) -> 1 | Z6: =IF($H6="Expert Level",1,0) -> 0 | AA6: =IF($H6="Intermediate Level",1,0) -> 0 | AC6: =N6 -> 5.2983674 | AD6: =G6 -> 304 | AE6: =J6 -> 30.5 | AF6: =IF($L6=2012,1,0) -> 0 | AG6: =IF($L6=2013,1,0) -> 0 | AH6: =IF($L6=2014,1,0) -> 0 | AI6: =IF($L6=2015,1,0) -> 0 | AJ6: =IF($L6=2016,1,0) -> 1 | AK6: =IF($L6=2017,1,0) -> 0 | AL6: =IF($H6="Beginner Level",1,0) -> 1 | AM6: =IF($H6="Expert Level",1,0) -> 0 | AN6: =IF($H6="Intermediate Level",1,0) -> 0
A7: 473160 | B7: Web Design for Web Developers: Build Beautiful Websites! | C7: https://www.udemy.com/web-design-secrets/ | D7: 0 | E7: 98867 | F7: 6512 | G7: 20 | H7: All Levels | I7: 0.82 | J7: 3 | K7: Free | L7: 2015 | M7: 11.501531 | N7: -4.6051702 | P7: =D7 -> 0 | Q7: =G7 -> 20 | R7: =J7 -> 3 | S7: =IF($L7=2012,1,0) -> 0 | T7: =IF($L7=2013,1,0) -> 0 | U7: =IF($L7=2014,1,0) -> 0 | V7: =IF($L7=2015,1,0) -> 1 | W7: =IF($L7=2016,1,0) -> 0 | X7: =IF($L7=2017,1,0) -> 0 | Y7: =IF($H7="Beginner Level",1,0) -> 0 | Z7: =IF($H7="Expert Level",1,0) -> 0 | AA7: =IF($H7="Intermediate Level",1,0) -> 0 | AC7: =N7 -> -4.6051702 | AD7: =G7 -> 20 | AE7: =J7 -> 3 | AF7: =IF($L7=2012,1,0) -> 0 | AG7: =IF($L7=2013,1,0) -> 0 | AH7: =IF($L7=2014,1,0) -> 0 | AI7: =IF($L7=2015,1,0) -> 1 | AJ7: =IF($L7=2016,1,0) -> 0 | AK7: =IF($L7=2017,1,0) -> 0 | AL7: =IF($H7="Beginner Level",1,0) -> 0 | AM7: =IF($H7="Expert Level",1,0) -> 0 | AN7: =IF($H7="Intermediate Level",1,0) -> 0
A8: 94430 | B8: Learn Javascript & JQuery From Scratch | C8: https://www.udemy.com/learn-javascript-jquery-from-scratch/ | D8: 30 | E8: 84897 | F8: 2685 | G8: 10 | H8: All Levels | I8: 0.79 | J8: 2 | K8: Paid | L8: 2013 | M8: 11.349194 | N8: 3.4015307 | P8: =D8 -> 30 | Q8: =G8 -> 10 | R8: =J8 -> 2 | S8: =IF($L8=2012,1,0) -> 0 | T8: =IF($L8=2013,1,0) -> 1 | U8: =IF($L8=2014,1,0) -> 0 | V8: =IF($L8=2015,1,0) -> 0 | W8: =IF($L8=2016,1,0) -> 0 | X8: =IF($L8=2017,1,0) -> 0 | Y8: =IF($H8="Beginner Level",1,0) -> 0 | Z8: =IF($H8="Expert Level",1,0) -> 0 | AA8: =IF($H8="Intermediate Level",1,0) -> 0 | AC8: =N8 -> 3.4015307 | AD8: =G8 -> 10 | AE8: =J8 -> 2 | AF8: =IF($L8=2012,1,0) -> 0 | AG8: =IF($L8=2013,1,0) -> 1 | AH8: =IF($L8=2014,1,0) -> 0 | AI8: =IF($L8=2015,1,0) -> 0 | AJ8: =IF($L8=2016,1,0) -> 0 | AK8: =IF($L8=2017,1,0) -> 0 | AL8: =IF($H8="Beginner Level",1,0) -> 0 | AM8: =IF($H8="Expert Level",1,0) -> 0 | AN8: =IF($H8="Intermediate Level",1,0) -> 0
A9: 130064 | B9: Practical PHP: Master the Basics and Code Dynamic Websites | C9: https://www.udemy.com/code-dynamic-websites/ | D9: 0 | E9: 83737 | F9: 4598 | G9: 45 | H9: Intermediate Level | I9: 0.85 | J9: 6.5 | K9: Free | L9: 2014 | M9: 11.335436 | N9: -4.6051702 | P9: =D9 -> 0 | Q9: =G9 -> 45 | R9: =J9 -> 6.5 | S9: =IF($L9=2012,1,0) -> 0 | T9: =IF($L9=2013,1,0) -> 0 | U9: =IF($L9=2014,1,0) -> 1 | V9: =IF($L9=2015,1,0) -> 0 | W9: =IF($L9=2016,1,0) -> 0 | X9: =IF($L9=2017,1,0) -> 0 | Y9: =IF($H9="Beginner Level",1,0) -> 0 | Z9: =IF($H9="Expert Level",1,0) -> 0 | AA9: =IF($H9="Intermediate Level",1,0) -> 1 | AC9: =N9 -> -4.6051702 | AD9: =G9 -> 45 | AE9: =J9 -> 6.5 | AF9: =IF($L9=2012,1,0) -> 0 | AG9: =IF($L9=2013,1,0) -> 0 | AH9: =IF($L9=2014,1,0) -> 1 | AI9: =IF($L9=2015,1,0) -> 0 | AJ9: =IF($L9=2016,1,0) -> 0 | AK9: =IF($L9=2017,1,0) -> 0 | AL9: =IF($H9="Beginner Level",1,0) -> 0 | AM9: =IF($H9="Expert Level",1,0) -> 0 | AN9: =IF($H9="Intermediate Level",1,0) -> 1
A10: 364426 | B10: JavaScript: Understanding the Weird Parts | C10: https://www.udemy.com/understand-javascript/ | D10: 175 | E10: 79612 | F10: 16976 | G10: 85 | H10: All Levels | I10: 0.69 | J10: 11.5 | K10: Paid | L10: 2015 | M10: 11.28492 | N10: 5.1648431 | P10: =D10 -> 175 | Q10: =G10 -> 85 | R10: =J10 -> 11.5 | S10: =IF($L10=2012,1,0) -> 0 | T10: =IF($L10=2013,1,0) -> 0 | U10: =IF($L10=2014,1,0) -> 0 | V10: =IF($L10=2015,1,0) -> 1 | W10: =IF($L10=2016,1,0) -> 0 | X10: =IF($L10=2017,1,0) -> 0 | Y10: =IF($H10="Beginner Level",1,0) -> 0 | Z10: =IF($H10="Expert Level",1,0) -> 0 | AA10: =IF($H10="Intermediate Level",1,0) -> 0 | AC10: =N10 -> 5.1648431 | AD10: =G10 -> 85 | AE10: =J10 -> 11.5 | AF10: =IF($L10=2012,1,0) -> 0 | AG10: =IF($L10=2013,1,0) -> 0 | AH10: =IF($L10=2014,1,0) -> 0 | AI10: =IF($L10=2015,1,0) -> 1 | AJ10: =IF($L10=2016,1,0) -> 0 | AK10: =IF($L10=2017,1,0) -> 0 | AL10: =IF($H10="Beginner Level",1,0) -> 0 | AM10: =IF($H10="Expert Level",1,0) -> 0 | AN10: =IF($H10="Intermediate Level",1,0) -> 0
A11: 756150 | B11: Angular 4 (formerly Angular 2) - The Complete Guide | C11: https://www.udemy.com/the-complete-guide-to-angular-2/ | D11: 190 | E11: 73783 | F11: 19649 | G11: 329 | H11: Beginner Level | I11: 0.9 | J11: 22 | K11: Paid | L11: 2016 | M11: 11.208884 | N11: 5.2470767 | P11: =D11 -> 190 | Q11: =G11 -> 329 | R11: =J11 -> 22 | S11: =IF($L11=2012,1,0) -> 0 | T11: =IF($L11=2013,1,0) -> 0 | U11: =IF($L11=2014,1,0) -> 0 | V11: =IF($L11=2015,1,0) -> 0 | W11: =IF($L11=2016,1,0) -> 1 | X11: =IF($L11=2017,1,0) -> 0 | Y11: =IF($H11="Beginner Level",1,0) -> 1 | Z11: =IF($H11="Expert Level",1,0) -> 0 | AA11: =IF($H11="Intermediate Level",1,0) -> 0 | AC11: =N11 -> 5.2470767 | AD11: =G11 -> 329 | AE11: =J11 -> 22 | AF11: =IF($L11=2012,1,0) -> 0 | AG11: =IF($L11=2013,1,0) -> 0 | AH11: =IF($L11=2014,1,0) -> 0 | AI11: =IF($L11=2015,1,0) -> 0 | AJ11: =IF($L11=2016,1,0) -> 1 | AK11: =IF($L11=2017,1,0) -> 0 | AL11: =IF($H11="Beginner Level",1,0) -> 1 | AM11: =IF($H11="Expert Level",1,0) -> 0 | AN11: =IF($H11="Intermediate Level",1,0) -> 0
A12: 21386 | B12: Beginner Photoshop to HTML5 and CSS3 | C12: https://www.udemy.com/psd-html5-css3/ | D12: 0 | E12: 73110 | F12: 1716 | G12: 22 | H12: All Levels | I12: 0.94 | J12: 2 | K12: Free | L12: 2012 | M12: 11.19972 | N12: -4.6051702 | P12: =D12 -> 0 | Q12: =G12 -> 22 | R12: =J12 -> 2 | S12: =IF($L12=2012,1,0) -> 1 | T12: =IF($L12=2013,1,0) -> 0 | U12: =IF($L12=2014,1,0) -> 0 | V12: =IF($L12=2015,1,0) -> 0 | W12: =IF($L12=2016,1,0) -> 0 | X12: =IF($L12=2017,1,0) -> 0 | Y12: =IF($H12="Beginner Level",1,0) -> 0 | Z12: =IF($H12="Expert Level",1,0) -> 0 | AA12: =IF($H12="Intermediate Level",1,0) -> 0 | AC12: =N12 -> -4.6051702 | AD12: =G12 -> 22 | AE12: =J12 -> 2 | AF12: =IF($L12=2012,1,0) -> 1 | AG12: =IF($L12=2013,1,0) -> 0 | AH12: =IF($L12=2014,1,0) -> 0 | AI12: =IF($L12=2015,1,0) -> 0 | AJ12: =IF($L12=2016,1,0) -> 0 | AK12: =IF($L12=2017,1,0) -> 0 | AL12: =IF($H12="Beginner Level",1,0) -> 0 | AM12: =IF($H12="Expert Level",1,0) -> 0 | AN12: =IF($H12="Intermediate Level",1,0) -> 0
A13: 65330 | B13: Web Development By Doing: HTML / CSS From Scratch | C13: https://www.udemy.com/web-development-learn-by-doing-html5-css3-from-scratch-introductory/ | D13: 0 | E13: 72932 | F13: 2575 | G13: 21 | H13: All Levels | I13: 0.39 | J13: 1 | K13: Free | L13: 2013 | M13: 11.197283 | N13: -4.6051702 | P13: =D13 -> 0 | Q13: =G13 -> 21 | R13: =J13 -> 1 | S13: =IF($L13=2012,1,0) -> 0 | T13: =IF($L13=2013,1,0) -> 1 | U13: =IF($L13=2014,1,0) -> 0 | V13: =IF($L13=2015,1,0) -> 0 | W13: =IF($L13=2016,1,0) -> 0 | X13: =IF($L13=2017,1,0) -> 0 | Y13: =IF($H13="Beginner Level",1,0) -> 0 | Z13: =IF($H13="Expert Level",1,0) -> 0 | AA13: =IF($H13="Intermediate Level",1,0) -> 0 | AC13: =N13 -> -4.6051702 | AD13: =G13 -> 21 | AE13: =J13 -> 1 | AF13: =IF($L13=2012,1,0) -> 0 | AG13: =IF($L13=2013,1,0) -> 1 | AH13: =IF($L13=2014,1,0) -> 0 | AI13: =IF($L13=2015,1,0) -> 0 | AJ13: =IF($L13=2016,1,0) -> 0 | AK13: =IF($L13=2017,1,0) -> 0 | AL13: =IF($H13="Beginner Level",1,0) -> 0 | AM13: =IF($H13="Expert Level",1,0) -> 0 | AN13: =IF($H13="Intermediate Level",1,0) -> 0
... A1204: 1270222 | B1204: Learning Path: Web Applications with Spring and Angular | C1204: https://www.udemy.com/learning-path-web-applications-with-spring-and-angular/ | D1204: 200 | E1204: 19 | F1204: 2 | G1204: 33 | H1204: Beginner Level | I1204: 0.12 | J1204: 4 | K1204: Paid | L1204: 2017 | M1204: 2.944439 | N1204: 5.2983674 | P1204: =D1204 -> 200 | Q1204: =G1204 -> 33 | R1204: =J1204 -> 4 | S1204: =IF($L1204=2012,1,0) -> 0 | T1204: =IF($L1204=2013,1,0) -> 0 | U1204: =IF($L1204=2014,1,0) -> 0 | V1204: =IF($L1204=2015,1,0) -> 0 | W1204: =IF($L1204=2016,1,0) -> 0 | X1204: =IF($L1204=2017,1,0) -> 1 | Y1204: =IF($H1204="Beginner Level",1,0) -> 1 | Z1204: =IF($H1204="Expert Level",1,0) -> 0 | AA1204: =IF($H1204="Intermediate Level",1,0) -> 0 | AC1204: =N1204 -> 5.2983674 | AD1204: =G1204 -> 33 | AE1204: =J1204 -> 4 | AF1204: =IF($L1204=2012,1,0) -> 0 | AG1204: =IF($L1204=2013,1,0) -> 0 | AH1204: =IF($L1204=2014,1,0) -> 0 | AI1204: =IF($L1204=2015,1,0) -> 0 | AJ1204: =IF($L1204=2016,1,0) -> 0 | AK1204: =IF($L1204=2017,1,0) -> 1 | AL1204: =IF($H1204="Beginner Level",1,0) -> 1 | AM1204: =IF($H1204="Expert Level",1,0) -> 0 | AN1204: =IF($H1204="Intermediate Level",1,0) -> 0

Sheet Q1_描述統計
A1: 問題一:描述性統計(公式即時計算)
A3: 變數 | B3: 平均數 | C3: 中位數 | D3: 眾數 | E3: 標準差 | F3: 最小值 | G3: 最大值
A4: price | B4: =AVERAGE(資料!D2:D1204) -> 77.036575 | C4: =MEDIAN(資料!D2:D1204) -> 50 | D4: =MODE(資料!D2:D1204) -> 20 | E4: =STDEV(資料!D2:D1204) -> 66.14542 | F4: =MIN(資料!D2:D1204) -> 0 | G4: =MAX(資料!D2:D1204) -> 200
A5: num_subscribers | B5: =AVERAGE(資料!E2:E1204) -> 6635.0249 | C5: =MEDIAN(資料!E2:E1204) -> 2430 | D5: =MODE(資料!E2:E1204) -> 578 | E5: =STDEV(資料!E2:E1204) -> 14559.419 | F5: =MIN(資料!E2:E1204) -> 19 | G5: =MAX(資料!E2:E1204) -> 268923
A6: num_reviews | B6: =AVERAGE(資料!F2:F1204) -> 357.35578 | C6: =MEDIAN(資料!F2:F1204) -> 65 | D6: =MODE(資料!F2:F1204) -> 16 | E6: =STDEV(資料!F2:F1204) -> 1572.9177 | F6: =MIN(資料!F2:F1204) -> 0 | G6: =MAX(資料!F2:F1204) -> 27445
A7: num_lectures | B7: =AVERAGE(資料!G2:G1204) -> 52.767249 | C7: =MEDIAN(資料!G2:G1204) -> 32 | D7: =MODE(資料!G2:G1204) -> 20 | E7: =STDEV(資料!G2:G1204) -> 62.762267 | F7: =MIN(資料!G2:G1204) -> 5 | G7: =MAX(資料!G2:G1204) -> 779
A8: rating | B8: =AVERAGE(資料!I2:I1204) -> 0.64305071 | C8: =MEDIAN(資料!I2:I1204) -> 0.76 | D8: =MODE(資料!I2:I1204) -> 0.96 | E8: =STDEV(資料!I2:I1204) -> 0.30600358 | F8: =MIN(資料!I2:I1204) -> 0 | G8: =MAX(資料!I2:I1204) -> 1
A9: content_duration | B9: =AVERAGE(資料!J2:J1204) -> 5.5866584 | C9: =MEDIAN(資料!J2:J1204) -> 3 | D9: =MODE(資料!J2:J1204) -> 1 | E9: =STDEV(資料!J2:J1204) -> 7.2428552 | F9: =MIN(資料!J2:J1204) -> 0.5 | G9: =MAX(資料!J2:J1204) -> 76.5
A11: 註:STDEV 為樣本標準差;MODE 取最小眾數。所有數值引用「資料」工作表,資料變動即自動更新。

Sheet Q2_頻數
A1: 問題二:level 與 year 的頻數分布
A3: level | B3: 次數 | C3: 占比 | D3: 公式
A4: All Levels | B4: =COUNTIF(資料!H2:H1204,A4) -> 633 | C4: =B4/1203 -> 0.52618454 | D4: COUNTIF(level 欄)
A5: Beginner Level | B5: =COUNTIF(資料!H2:H1204,A5) -> 422 | C5: =B5/1203 -> 0.35078969 | D5: COUNTIF(level 欄)
A6: Intermediate Level | B6: =COUNTIF(資料!H2:H1204,A6) -> 134 | C6: =B6/1203 -> 0.1113882 | D6: COUNTIF(level 欄)
A7: Expert Level | B7: =COUNTIF(資料!H2:H1204,A7) -> 14 | C7: =B7/1203 -> 0.011637573 | D7: COUNTIF(level 欄)
A9: year | B9: 次數 | C9: 占比 | D9: 公式
A10: 2011 | B10: =COUNTIF(資料!L2:L1204,A10) -> 5 | C10: =B10/1203 -> 0.004156276 | D10: COUNTIF(year 欄)
A11: 2012 | B11: =COUNTIF(資料!L2:L1204,A11) -> 19 | C11: =B11/1203 -> 0.015793849 | D11: COUNTIF(year 欄)
A12: 2013 | B12: =COUNTIF(資料!L2:L1204,A12) -> 55 | C12: =B12/1203 -> 0.045719036 | D12: COUNTIF(year 欄)
A13: 2014 | B13: =COUNTIF(資料!L2:L1204,A13) -> 115 | C13: =B13/1203 -> 0.095594347 | D13: COUNTIF(year 欄)
A14: 2015 | B14: =COUNTIF(資料!L2:L1204,A14) -> 336 | C14: =B14/1203 -> 0.27930175 | D14: COUNTIF(year 欄)
A15: 2016 | B15: =COUNTIF(資料!L2:L1204,A15) -> 449 | C15: =B15/1203 -> 0.37323358 | D15: COUNTIF(year 欄)
A16: 2017 | B16: =COUNTIF(資料!L2:L1204,A16) -> 224 | C16: =B16/1203 -> 0.18620116 | D16: COUNTIF(year 欄)

Sheet Q3_t檢定
A1: 問題三:單樣本 t 檢定 — 平均評分是否 = 0.65
A2: H0:母體平均評分 = 0.65 H1:母體平均評分 ≠ 0.65(雙尾,顯著水準 5%)
A4: 樣本數 n | B4: =COUNT(資料!I2:I1204) -> 1203
A5: 樣本平均數 | B5: =AVERAGE(資料!I2:I1204) -> 0.64305071
A6: 樣本標準差 | B6: =STDEV(資料!I2:I1204) -> 0.30600358
A7: 檢定值 μ0 | B7: 0.65
A8: 標準誤 SE | B8: =B6/SQRT(B4) -> 0.0088225411
A9: t 統計量 | B9: =(B5-B7)/B8 -> -0.78767481
A10: 自由度 df | B10: =B4-1 -> 1202
A11: p 值(雙尾) | B11: =TDIST(ABS(B9),B10,2) -> 0.43104223
A13: 結論
A14: =IF(B11<0.05,"p < 0.05,拒絕 H0:平均評分與 65% 有顯著差異。","p = "&TEXT(B11,"0.000")&" ≥ 0.05,無法拒絕 H0:平均評分與 65% 無顯著差異。") -> p = 0.431 ≥ 0.05,無法拒絕 H0:平均評分與 65% 無顯著差異。

Sheet Q4_相關
A1: 問題四:price 與 num_subscribers 的相關性
A3: 項目 | B3: 值 | C3: 說明
A4: 預測(需求法則) | B4: 負相關 | C4: 價格上升→需求下降
A5: Pearson 相關係數 | B5: =CORREL(資料!D2:D1204,資料!E2:E1204) -> 0.013978844 | C5: CORREL(price, num_subscribers)
A7: 結論
A8: 相關係數接近於零,與「負相關」的預測不符。可能原因:免費課程(price=0)訂閱數極高、價格內生於課程品質。詳見報告問題四。

Sheet Q5_Q10_迴歸
A1: 問題五、十:迴歸分析(以 LINEST 估計)
A3: 簡單迴歸(Q5):num_subscribers ~ price
A4: 項目 | B4: 係數 | C4: 標準誤 | D4: t 值 | E4: p 值
A5: 截距 (Intercept) | B5: =INDEX(LINEST(資料!E2:E1204,資料!D2:D1204,TRUE(),TRUE()),1,2) -> 6397.9899 | C5: =INDEX(LINEST(資料!E2:E1204,資料!D2:D1204,TRUE(),TRUE()),2,2) -> 644.73299 | D5: =B5/C5 -> 9.9234722 | E5: =TDIST(ABS(D5),$C$8,2) -> 2.3220749e-22
A6: price | B6: =INDEX(LINEST(資料!E2:E1204,資料!D2:D1204,TRUE(),TRUE()),1,1) -> 3.0769152 | C6: =INDEX(LINEST(資料!E2:E1204,資料!D2:D1204,TRUE(),TRUE()),2,1) -> 6.3508276 | D6: =B6/C6 -> 0.48449043 | E6: =TDIST(ABS(D6),$C$8,2) -> 0.6281262
A8: 自由度 df | B8: =INDEX(LINEST(資料!E2:E1204,資料!D2:D1204,TRUE(),TRUE()),4,2) -> 1201 | C8: =INDEX(LINEST(資料!E2:E1204,資料!D2:D1204,TRUE(),TRUE()),4,2) -> 1201 | D8: R² | E8: =INDEX(LINEST(資料!E2:E1204,資料!D2:D1204,TRUE(),TRUE()),3,1) -> 0.00019540808
A11: 多元迴歸(Q5):num_subscribers ~ price + 控制變數
A12: 項目 | B12: 係數 | C12: 標準誤 | D12: t 值 | E12: p 值
A13: 截距 (Intercept) | B13: =INDEX(LINEST(資料!E2:E1204,資料!P2:AA1204,TRUE(),TRUE()),1,13) -> 20778.842 | C13: =INDEX(LINEST(資料!E2:E1204,資料!P2:AA1204,TRUE(),TRUE()),2,13) -> 6229.2562 | D13: =B13/C13 -> 3.3356859 | E13: =TDIST(ABS(D13),$C$27,2) -> 0.00087714179
A14: price | B14: =INDEX(LINEST(資料!E2:E1204,資料!P2:AA1204,TRUE(),TRUE()),1,12) -> -4.4253245 | C14: =INDEX(LINEST(資料!E2:E1204,資料!P2:AA1204,TRUE(),TRUE()),2,12) -> 6.6833872 | D14: =B14/C14 -> -0.66213799 | E14: =TDIST(ABS(D14),$C$27,2) -> 0.508011
A15: num_lectures | B15: =INDEX(LINEST(資料!E2:E1204,資料!P2:AA1204,TRUE(),TRUE()),1,11) -> 0.22626879 | C15: =INDEX(LINEST(資料!E2:E1204,資料!P2:AA1204,TRUE(),TRUE()),2,11) -> 12.609639 | D15: =B15/C15 -> 0.017944114 | E15: =TDIST(ABS(D15),$C$27,2) -> 0.98568644
A16: content_duration | B16: =INDEX(LINEST(資料!E2:E1204,資料!P2:AA1204,TRUE(),TRUE()),1,10) -> 300.73031 | C16: =INDEX(LINEST(資料!E2:E1204,資料!P2:AA1204,TRUE(),TRUE()),2,10) -> 108.60606 | D16: =B16/C16 -> 2.7690013 | E16: =TDIST(ABS(D16),$C$27,2) -> 0.0057101726
A17: year:2012 | B17: =INDEX(LINEST(資料!E2:E1204,資料!P2:AA1204,TRUE(),TRUE()),1,9) -> -6174.2817 | C17: =INDEX(LINEST(資料!E2:E1204,資料!P2:AA1204,TRUE(),TRUE()),2,9) -> 6954.1326 | D17: =B17/C17 -> -0.88785792 | E17: =TDIST(ABS(D17),$C$27,2) -> 0.3747966
A18: year:2013 | B18: =INDEX(LINEST(資料!E2:E1204,資料!P2:AA1204,TRUE(),TRUE()),1,8) -> -1641.5042 | C18: =INDEX(LINEST(資料!E2:E1204,資料!P2:AA1204,TRUE(),TRUE()),2,8) -> 6480.0936 | D18: =B18/C18 -> -0.25331489 | E18: =TDIST(ABS(D18),$C$27,2) -> 0.80006865
A19: year:2014 | B19: =INDEX(LINEST(資料!E2:E1204,資料!P2:AA1204,TRUE(),TRUE()),1,7) -> -12845.698 | C19: =INDEX(LINEST(資料!E2:E1204,資料!P2:AA1204,TRUE(),TRUE()),2,7) -> 6339.8248 | D19: =B19/C19 -> -2.0261914 | E19: =TDIST(ABS(D19),$C$27,2) -> 0.042967896
A20: year:2015 | B20: =INDEX(LINEST(資料!E2:E1204,資料!P2:AA1204,TRUE(),TRUE()),1,6) -> -15160.559 | C20: =INDEX(LINEST(資料!E2:E1204,資料!P2:AA1204,TRUE(),TRUE()),2,6) -> 6250.4142 | D20: =B20/C20 -> -2.4255287 | E20: =TDIST(ABS(D20),$C$27,2) -> 0.015434069
A21: year:2016 | B21: =INDEX(LINEST(資料!E2:E1204,資料!P2:AA1204,TRUE(),TRUE()),1,5) -> -17797.35 | C21: =INDEX(LINEST(資料!E2:E1204,資料!P2:AA1204,TRUE(),TRUE()),2,5) -> 6238.689 | D21: =B21/C21 -> -2.8527387 | E21: =TDIST(ABS(D21),$C$27,2) -> 0.0044094355
A22: year:2017 | B22: =INDEX(LINEST(資料!E2:E1204,資料!P2:AA1204,TRUE(),TRUE()),1,4) -> -19433.136 | C22: =INDEX(LINEST(資料!E2:E1204,資料!P2:AA1204,TRUE(),TRUE()),2,4) -> 6278.6368 | D22: =B22/C22 -> -3.0951202 | E22: =TDIST(ABS(D22),$C$27,2) -> 0.0020132566
A23: level:Beginner | B23: =INDEX(LINEST(資料!E2:E1204,資料!P2:AA1204,TRUE(),TRUE()),1,3) -> 1038.5159 | C23: =INDEX(LINEST(資料!E2:E1204,資料!P2:AA1204,TRUE(),TRUE()),2,3) -> 870.20108 | D23: =B23/C23 -> 1.1934206 | E23: =TDIST(ABS(D23),$C$27,2) -> 0.23294256
A24: level:Expert | B24: =INDEX(LINEST(資料!E2:E1204,資料!P2:AA1204,TRUE(),TRUE()),1,2) -> 8671.5445 | C24: =INDEX(LINEST(資料!E2:E1204,資料!P2:AA1204,TRUE(),TRUE()),2,2) -> 3744.4052 | D24: =B24/C24 -> 2.315867 | E24: =TDIST(ABS(D24),$C$27,2) -> 0.020734835
A25: level:Intermediate | B25: =INDEX(LINEST(資料!E2:E1204,資料!P2:AA1204,TRUE(),TRUE()),1,1) -> -576.24929 | C25: =INDEX(LINEST(資料!E2:E1204,資料!P2:AA1204,TRUE(),TRUE()),2,1) -> 1318.5226 | D25: =B25/C25 -> -0.43704164 | E25: =TDIST(ABS(D25),$C$27,2) -> 0.66216044
A27: 自由度 df | B27: =INDEX(LINEST(資料!E2:E1204,資料!P2:AA1204,TRUE(),TRUE()),4,2) -> 1190 | C27: =INDEX(LINEST(資料!E2:E1204,資料!P2:AA1204,TRUE(),TRUE()),4,2) -> 1190 | D27: R² | E27: =INDEX(LINEST(資料!E2:E1204,資料!P2:AA1204,TRUE(),TRUE()),3,1) -> 0.10779687
A30: 對數—對數迴歸(Q10):log(subs) ~ log(price) + 控制變數
A31: 項目 | B31: 係數 | C31: 標準誤 | D31: t 值 | E31: p 值
A32: 截距 (Intercept) | B32: =INDEX(LINEST(資料!M2:M1204,資料!AC2:AN1204,TRUE(),TRUE()),1,13) -> 9.7487601 | C32: =INDEX(LINEST(資料!M2:M1204,資料!AC2:AN1204,TRUE(),TRUE()),2,13) -> 0.53170316 | D32: =B32/C32 -> 18.334967 | E32: =TDIST(ABS(D32),$C$46,2) -> 2.4994979e-66
A33: log(price) | B33: =INDEX(LINEST(資料!M2:M1204,資料!AC2:AN1204,TRUE(),TRUE()),1,12) -> -0.15435116 | C33: =INDEX(LINEST(資料!M2:M1204,資料!AC2:AN1204,TRUE(),TRUE()),2,12) -> 0.012404544 | D33: =B33/C33 -> -12.443114 | E33: =TDIST(ABS(D33),$C$46,2) -> 1.6744053e-33
A34: num_lectures | B34: =INDEX(LINEST(資料!M2:M1204,資料!AC2:AN1204,TRUE(),TRUE()),1,11) -> 0.0016423111 | C34: =INDEX(LINEST(資料!M2:M1204,資料!AC2:AN1204,TRUE(),TRUE()),2,11) -> 0.0010683067 | D34: =B34/C34 -> 1.537303 | E34: =TDIST(ABS(D34),$C$46,2) -> 0.12448496
A35: content_duration | B35: =INDEX(LINEST(資料!M2:M1204,資料!AC2:AN1204,TRUE(),TRUE()),1,10) -> 0.021661353 | C35: =INDEX(LINEST(資料!M2:M1204,資料!AC2:AN1204,TRUE(),TRUE()),2,10) -> 0.0092205727 | D35: =B35/C35 -> 2.3492416 | E35: =TDIST(ABS(D35),$C$46,2) -> 0.018974485
A36: year:2012 | B36: =INDEX(LINEST(資料!M2:M1204,資料!AC2:AN1204,TRUE(),TRUE()),1,9) -> -0.55551845 | C36: =INDEX(LINEST(資料!M2:M1204,資料!AC2:AN1204,TRUE(),TRUE()),2,9) -> 0.59251677 | D36: =B36/C36 -> -0.93755736 | E36: =TDIST(ABS(D36),$C$46,2) -> 0.34866217
A37: year:2013 | B37: =INDEX(LINEST(資料!M2:M1204,資料!AC2:AN1204,TRUE(),TRUE()),1,8) -> -0.5918486 | C37: =INDEX(LINEST(資料!M2:M1204,資料!AC2:AN1204,TRUE(),TRUE()),2,8) -> 0.5517033 | D37: =B37/C37 -> -1.0727661 | E37: =TDIST(ABS(D37),$C$46,2) -> 0.28359357
A38: year:2014 | B38: =INDEX(LINEST(資料!M2:M1204,資料!AC2:AN1204,TRUE(),TRUE()),1,7) -> -1.1421994 | C38: =INDEX(LINEST(資料!M2:M1204,資料!AC2:AN1204,TRUE(),TRUE()),2,7) -> 0.54036346 | D38: =B38/C38 -> -2.1137614 | E38: =TDIST(ABS(D38),$C$46,2) -> 0.034743284
A39: year:2015 | B39: =INDEX(LINEST(資料!M2:M1204,資料!AC2:AN1204,TRUE(),TRUE()),1,6) -> -1.3783082 | C39: =INDEX(LINEST(資料!M2:M1204,資料!AC2:AN1204,TRUE(),TRUE()),2,6) -> 0.53215043 | D39: =B39/C39 -> -2.5900725 | E39: =TDIST(ABS(D39),$C$46,2) -> 0.009712786
A40: year:2016 | B40: =INDEX(LINEST(資料!M2:M1204,資料!AC2:AN1204,TRUE(),TRUE()),1,5) -> -1.7521647 | C40: =INDEX(LINEST(資料!M2:M1204,資料!AC2:AN1204,TRUE(),TRUE()),2,5) -> 0.53109447 | D40: =B40/C40 -> -3.2991583 | E40: =TDIST(ABS(D40),$C$46,2) -> 0.00099845916
A41: year:2017 | B41: =INDEX(LINEST(資料!M2:M1204,資料!AC2:AN1204,TRUE(),TRUE()),1,4) -> -2.2314897 | C41: =INDEX(LINEST(資料!M2:M1204,資料!AC2:AN1204,TRUE(),TRUE()),2,4) -> 0.53430539 | D41: =B41/C41 -> -4.1764313 | E41: =TDIST(ABS(D41),$C$46,2) -> 3.1772633e-05
A42: level:Beginner | B42: =INDEX(LINEST(資料!M2:M1204,資料!AC2:AN1204,TRUE(),TRUE()),1,3) -> 0.024400244 | C42: =INDEX(LINEST(資料!M2:M1204,資料!AC2:AN1204,TRUE(),TRUE()),2,3) -> 0.074112125 | D42: =B42/C42 -> 0.32923417 | E42: =TDIST(ABS(D42),$C$46,2) -> 0.74203663
A43: level:Expert | B43: =INDEX(LINEST(資料!M2:M1204,資料!AC2:AN1204,TRUE(),TRUE()),1,2) -> 0.0032319967 | C43: =INDEX(LINEST(資料!M2:M1204,資料!AC2:AN1204,TRUE(),TRUE()),2,2) -> 0.31903409 | D43: =B43/C43 -> 0.010130569 | E43: =TDIST(ABS(D43),$C$46,2) -> 0.99191881
A44: level:Intermediate | B44: =INDEX(LINEST(資料!M2:M1204,資料!AC2:AN1204,TRUE(),TRUE()),1,1) -> 0.15485335 | C44: =INDEX(LINEST(資料!M2:M1204,資料!AC2:AN1204,TRUE(),TRUE()),2,1) -> 0.11231257 | D44: =B44/C44 -> 1.3787713 | E44: =TDIST(ABS(D44),$C$46,2) -> 0.16822438
A46: 自由度 df | B46: =INDEX(LINEST(資料!M2:M1204,資料!AC2:AN1204,TRUE(),TRUE()),4,2) -> 1190 | C46: =INDEX(LINEST(資料!M2:M1204,資料!AC2:AN1204,TRUE(),TRUE()),4,2) -> 1190 | D46: R² | E46: =INDEX(LINEST(資料!M2:M1204,資料!AC2:AN1204,TRUE(),TRUE()),3,1) -> 0.22944352
A48: 註:LINEST 第 4 引數=TRUE 時回傳完整統計量;係數列順序與自變數欄相反,本表已重新對應標籤。

Sheet Q11_需求曲線
A1: 問題十一:線性需求曲線(預測訂閱人數)
A2: 課程特徵:50 則講座、課程時長 10 小時、2017 年、Beginner 程度
A4: 價格 (USD) | B4: 預測訂閱人數 | C4: 預測方程
A5: 0 | B5: =Q5_Q10_迴歸!B13 + Q5_Q10_迴歸!B14*A5 + Q5_Q10_迴歸!B15*50 + Q5_Q10_迴歸!B16*10 + Q5_Q10_迴歸!B22 + Q5_Q10_迴歸!B23 -> 5402.8386 | C5: 截距+price係數×價格+其餘特徵
A6: 50 | B6: =Q5_Q10_迴歸!B13 + Q5_Q10_迴歸!B14*A6 + Q5_Q10_迴歸!B15*50 + Q5_Q10_迴歸!B16*10 + Q5_Q10_迴歸!B22 + Q5_Q10_迴歸!B23 -> 5181.5724 | C6: 截距+price係數×價格+其餘特徵
A7: 100 | B7: =Q5_Q10_迴歸!B13 + Q5_Q10_迴歸!B14*A7 + Q5_Q10_迴歸!B15*50 + Q5_Q10_迴歸!B16*10 + Q5_Q10_迴歸!B22 + Q5_Q10_迴歸!B23 -> 4960.3062 | C7: 截距+price係數×價格+其餘特徵
A8: 150 | B8: =Q5_Q10_迴歸!B13 + Q5_Q10_迴歸!B14*A8 + Q5_Q10_迴歸!B15*50 + Q5_Q10_迴歸!B16*10 + Q5_Q10_迴歸!B22 + Q5_Q10_迴歸!B23 -> 4739.0399 | C8: 截距+price係數×價格+其餘特徵
A9: 200 | B9: =Q5_Q10_迴歸!B13 + Q5_Q10_迴歸!B14*A9 + Q5_Q10_迴歸!B15*50 + Q5_Q10_迴歸!B16*10 + Q5_Q10_迴歸!B22 + Q5_Q10_迴歸!B23 -> 4517.7737 | C9: 截距+price係數×價格+其餘特徵
A11: 斜率(每 +1 美元的訂閱變化) | C11: =Q5_Q10_迴歸!B14 -> -4.4253245
A13: 此為向下傾斜的線性需求曲線;斜率即多元迴歸的 price 係數。詳見報告問題十一與圖 7。
